{
  "project_info": {
    "project_number": "66157506585",
    "project_id": "goldbullion-f4de4",
    "storage_bucket": "goldbullion-f4de4.appspot.com"
  },
  "client": [
    {
      "client_info": {
        "mobilesdk_app_id": "1:66157506585:android:f7d1d860a23ff076b47a88",
        "android_client_info": {
          "package_name": "com.goldbullion"
        }
      },
      "oauth_client": [],
      "api_key": [
        {
          "current_key": "AIzaSyDHrpaApCkj3FpMnS8SPuUsIX5WwruH_u4"
        }
      ],
      "services": {
        "appinvite_service": {
          "other_platform_oauth_client": []
        }
      }
    }
  ],
  "configuration_version": "1"
}